.DS_Store
README.md
requirements.txt
script.py
setup.py
Beamer/Prediction_Project.pdf
Beamer/beamer
Beamer/carte_de_france.pdf
Beamer/carte_de_france.png
Test/test_Project.py
Test/__pycache__/test_ClassModel.cpython-39-pytest-6.2.4.pyc
Test/__pycache__/test_Project.cpython-39-pytest-6.2.4.pyc
docs/.DS_Store
docs/Makefile
docs/conf.py
docs/index.rst
docs/make.bat
docs/requirements.txt
docs/Example/Example.rst
docs/Example/Example2.rst
docs/Example/Figure_1.pdf
docs/Example/carte.html
docs/Maps/Chro.rst
docs/Maps/ConsBy.rst
docs/Maps/carte_de_france.pdf
docs/Prediction/DataCollection.rst
docs/Prediction/Prediction.rst
docs/_build/.DS_Store
docs/_build/doctrees/environment.pickle
docs/_build/doctrees/index.doctree
docs/_build/doctrees/Example/Example.doctree
docs/_build/doctrees/Example/Example2.doctree
docs/_build/doctrees/Maps/Chro.doctree
docs/_build/doctrees/Maps/ConsBy.doctree
docs/_build/doctrees/Prediction/DataCollection.doctree
docs/_build/doctrees/Prediction/Prediction.doctree
docs/_build/html/.buildinfo
docs/_build/html/genindex.html
docs/_build/html/index.html
docs/_build/html/objects.inv
docs/_build/html/py-modindex.html
docs/_build/html/search.html
docs/_build/html/searchindex.js
docs/_build/html/Example/Example.html
docs/_build/html/Example/Example2.html
docs/_build/html/Maps/Chro.html
docs/_build/html/Maps/ConsBy.html
docs/_build/html/Prediction/DataCollection.html
docs/_build/html/Prediction/Prediction.html
docs/_build/html/_images/Figure_1.pdf
docs/_build/html/_images/ts.gif
docs/_build/html/_modules/index.html
docs/_build/html/_modules/Project/Map/ConsumptionBy.html
docs/_build/html/_modules/Project/Prediction/ClassModel.html
docs/_build/html/_modules/Project/Prediction/DataCollection.html
docs/_build/html/_sources/index.rst.txt
docs/_build/html/_sources/Example/Example.rst.txt
docs/_build/html/_sources/Example/Example2.rst.txt
docs/_build/html/_sources/Maps/Chro.rst.txt
docs/_build/html/_sources/Maps/ConsBy.rst.txt
m_dos.egg-info/PKG-INFO
m_dos.egg-info/SOURCES.txt
m_dos.egg-info/dependency_links.txt
m_dos.egg-info/not-zip-safe
m_dos.egg-info/top_level.txt
