Metadata-Version: 2.1
Name: m-dos
Version: 0.0.1
Summary: France energy prediction
Home-page: https://github.com/otmaneelallaki/HAX712X-DOS
Author: DOS
Author-email: otmane.allai1@gmail.com
License: MIT
Platform: UNKNOWN
